Workbook

Sheet Como usar
A1: Campo | B1: Orientação
A2: Plano | B2: 100 etapas; 1.000 subetapas; todos os estados iniciais pendentes.
A3: Subetapas | B3: Preencha estado e evidência. Concluída sem evidência não conta como verificada.
A4: Etapas | B4: Preencha responsável nominal, revisor, evidência do entregável e aceite validado.
A5: Conclusão | B5: A fórmula exige 10 subetapas verificadas e fechamento dos requisitos e dependências.
A6: Fórmulas | B6: O aplicativo de planilha recalcula ao abrir. A estrutura contém fórmulas em inglês no padrão XLSX.
A7: Revisão | B7: As fórmulas conferem preenchimento, não autenticidade de evidências ou identidade do revisor.
A8: Versões | B8: CSV e PDF são fotografias iniciais. Planilha e checklist HTML são registros independentes; escolha o registro oficial da equipe.
A9: Prazo | B9: Etapa não equivale a dia. Esforço e calendário dependem da etapa 10.
A10: Catálogo | B10: doufsxqlfjyuvxuezpln: somente consulta. Não escrever estoque, preço ou produto mestre.
A11: Banco próprio | B11: cfmzkthhgliqelozlmwu: operação do portal e snapshots históricos.
A12: Produção | B12: Conclusão do portal exige evidências de operação real conforme etapas 96–100.
A13: Referência | B13: Diagnóstico anterior e fontes técnicas na aba Referências.

Sheet Resumo
A1: Indicador | B1: Valor
A2: Etapas totais | B2: 100
A3: Subetapas totais | B3: 1000
A4: Subetapas verificadas | B4: =SUM(Subetapas!G2:G1001)
A5: Etapas concluídas | B5: =COUNTIF(Etapas!N2:N101,"Concluída")
A6: Avanço das subetapas | B6: =B4/B3
A7: Avanço das etapas | B7: =B5/B2
A8: Bloco | B8: Etapas concluídas
A9: Diagnóstico e estratégia | B9: =COUNTIFS(Etapas!B2:B101,A9,Etapas!N2:N101,"Concluída")
A10: Fundamentos e segurança | B10: =COUNTIFS(Etapas!B2:B101,A10,Etapas!N2:N101,"Concluída")
A11: Estrutura e conteúdo | B11: =COUNTIFS(Etapas!B2:B101,A11,Etapas!N2:N101,"Concluída")
A12: Sistema visual | B12: =COUNTIFS(Etapas!B2:B101,A12,Etapas!N2:N101,"Concluída")
A13: Catálogo e decisão | B13: =COUNTIFS(Etapas!B2:B101,A13,Etapas!N2:N101,"Concluída")
A14: Campanhas e propostas | B14: =COUNTIFS(Etapas!B2:B101,A14,Etapas!N2:N101,"Concluída")
A15: Governança e aprovações | B15: =COUNTIFS(Etapas!B2:B101,A15,Etapas!N2:N101,"Concluída")
A16: Execução e pós-compra | B16: =COUNTIFS(Etapas!B2:B101,A16,Etapas!N2:N101,"Concluída")
A17: Qualidade e validação | B17: =COUNTIFS(Etapas!B2:B101,A17,Etapas!N2:N101,"Concluída")
A18: Produção e expansão | B18: =COUNTIFS(Etapas!B2:B101,A18,Etapas!N2:N101,"Concluída")

Sheet Etapas
A1: Etapa | B1: Bloco | C1: Título | D1: Responsável funcional | E1: Dependências | F1: Entregável | G1: Critério obrigatório | H1: Subetapas verificadas | I1: Dependências concluídas | J1: Responsável nominal | K1: Revisor | L1: Evidência do entregável | M1: Aceite validado | N1: Estado calculado
A2: E001 | B2: Diagnóstico e estratégia | C2: Fixar o ponto de partida verificável | D2: Liderança técnica e Produto | E2: Nenhuma | F2: Inventário do ambiente e matriz de capacidades | G2: Cada capacidade possui origem, estado observado e responsável; produção não é inferida pelo README. | H2: =COUNTIFS(Subetapas!A$2:A$1001,A2,Subetapas!G$2:G$1001,1) | I2: =IF(TRUE,"Sim","Não") | M2: Não | N2: =IF(AND(H2=10,I2="Sim",LEN(TRIM(J2))>0,LEN(TRIM(K2))>0,LEN(TRIM(L2))>0,M2="Sim"),"Concluída",IF(H2=10,"Revisão ou dependências pendentes",IF(H2>0,"Em andamento","Pendente")))
A3: E002 | B3: Diagnóstico e estratégia | C3: Conter exposição de credenciais e ferramentas de teste | D3: Engenharia de segurança | E3: E001 | F3: Superfície de acesso emergencial corrigida | G3: Nenhuma função publicada devolve segredos; o tratamento da exposição potencial está documentado. | H3: =COUNTIFS(Subetapas!A$2:A$1001,A3,Subetapas!G$2:G$1001,1) | I3: =IF(AND(N2="Concluída"),"Sim","Não") | M3: Não | N3: =IF(AND(H3=10,I3="Sim",LEN(TRIM(J3))>0,LEN(TRIM(K3))>0,LEN(TRIM(L3))>0,M3="Sim"),"Concluída",IF(H3=10,"Revisão ou dependências pendentes",IF(H3>0,"Em andamento","Pendente")))
A4: E003 | B4: Diagnóstico e estratégia | C4: Garantir catálogo externo exclusivamente de consulta | D4: Engenharia de dados e Backend | E4: E001, E002 | F4: Contrato de integração somente leitura | G4: API e identidade de origem impedem gravações; amostra de leitura identifica corretamente o banco mestre. | H4: =COUNTIFS(Subetapas!A$2:A$1001,A4,Subetapas!G$2:G$1001,1) | I4: =IF(AND(N2="Concluída",N3="Concluída"),"Sim","Não") | M4: Não | N4: =IF(AND(H4=10,I4="Sim",LEN(TRIM(J4))>0,LEN(TRIM(K4))>0,LEN(TRIM(L4))>0,M4="Sim"),"Concluída",IF(H4=10,"Revisão ou dependências pendentes",IF(H4>0,"Em andamento","Pendente")))
A5: E004 | B5: Diagnóstico e estratégia | C5: Planejar pesquisa com compradores e marketing | D5: Pesquisa UX e Produto | E5: E001 | F5: Plano de pesquisa e recrutamento consentido | G5: Amostra cobre papéis e cooperativas distintas; observações são separadas de hipóteses. | H5: =COUNTIFS(Subetapas!A$2:A$1001,A5,Subetapas!G$2:G$1001,1) | I5: =IF(AND(N2="Concluída"),"Sim","Não") | M5: Não | N5: =IF(AND(H5=10,I5="Sim",LEN(TRIM(J5))>0,LEN(TRIM(K5))>0,LEN(TRIM(L5))>0,M5="Sim"),"Concluída",IF(H5=10,"Revisão ou dependências pendentes",IF(H5>0,"Em andamento","Pendente")))
A6: E005 | B6: Diagnóstico e estratégia | C6: Definir perfis funcionais e trabalhos a realizar | D6: Pesquisa UX e Estratégia | E6: E004 | F6: Perfis funcionais ligados a tarefas | G6: Cada perfil tem objetivo, contexto, dificuldade observada e critério de sucesso verificável. | H6: =COUNTIFS(Subetapas!A$2:A$1001,A6,Subetapas!G$2:G$1001,1) | I6: =IF(AND(N5="Concluída"),"Sim","Não") | M6: Não | N6: =IF(AND(H6=10,I6="Sim",LEN(TRIM(J6))>0,LEN(TRIM(K6))>0,LEN(TRIM(L6))>0,M6="Sim"),"Concluída",IF(H6=10,"Revisão ou dependências pendentes",IF(H6>0,"Em andamento","Pendente")))
A7: E006 | B7: Diagnóstico e estratégia | C7: Mapear a jornada atual e a jornada pretendida | D7: Estratégia de serviço e UX | E7: E004, E005 | F7: Mapas de jornada atual e futura | G7: Todas as passagens entre solicitação e recebimento têm ator, informação e dificuldade identificados. | H7: =COUNTIFS(Subetapas!A$2:A$1001,A7,Subetapas!G$2:G$1001,1) | I7: =IF(AND(N5="Concluída",N6="Concluída"),"Sim","Não") | M7: Não | N7: =IF(AND(H7=10,I7="Sim",LEN(TRIM(J7))>0,LEN(TRIM(K7))>0,LEN(TRIM(L7))>0,M7="Sim"),"Concluída",IF(H7=10,"Revisão ou dependências pendentes",IF(H7>0,"Em andamento","Pendente")))
A8: E007 | B8: Diagnóstico e estratégia | C8: Desenhar o serviço por trás da interface | D8: Estratégia de serviço e Operação | E8: E006 | F8: Mapa de serviço com responsabilidades | G8: Cada promessa exibida possui processo, sistema responsável e tratamento de falha. | H8: =COUNTIFS(Subetapas!A$2:A$1001,A8,Subetapas!G$2:G$1001,1) | I8: =IF(AND(N7="Concluída"),"Sim","Não") | M8: Não | N8: =IF(AND(H8=10,I8="Sim",LEN(TRIM(J8))>0,LEN(TRIM(K8))>0,LEN(TRIM(L8))>0,M8="Sim"),"Concluída",IF(H8=10,"Revisão ou dependências pendentes",IF(H8>0,"Em andamento","Pendente")))
A9: E008 | B9: Diagnóstico e estratégia | C9: Configurar governança por cooperativa | D9: Produto e responsáveis de compras | E9: E004, E007 | F9: Matriz de políticas locais versionadas | G9: Duas políticas distintas podem ser representadas sem criar regra nacional fictícia. | H9: =COUNTIFS(Subetapas!A$2:A$1001,A9,Subetapas!G$2:G$1001,1) | I9: =IF(AND(N5="Concluída",N8="Concluída"),"Sim","Não") | M9: Não | N9: =IF(AND(H9=10,I9="Sim",LEN(TRIM(J9))>0,LEN(TRIM(K9))>0,LEN(TRIM(L9))>0,M9="Sim"),"Concluída",IF(H9=10,"Revisão ou dependências pendentes",IF(H9>0,"Em andamento","Pendente")))
A10: E009 | B10: Diagnóstico e estratégia | C10: Definir resultados e instrumentos de medição | D10: Produto e Dados | E10: E005, E006 | F10: Dicionário inicial de indicadores | G10: Cada indicador tem evento de origem, denominador, período e limitação; ausência de medição é explícita. | H10: =COUNTIFS(Subetapas!A$2:A$1001,A10,Subetapas!G$2:G$1001,1) | I10: =IF(AND(N6="Concluída",N7="Concluída"),"Sim","Não") | M10: Não | N10: =IF(AND(H10=10,I10="Sim",LEN(TRIM(J10))>0,LEN(TRIM(K10))>0,LEN(TRIM(L10))>0,M10="Sim"),"Concluída",IF(H10=10,"Revisão ou dependências pendentes",IF(H10>0,"Em andamento","Pendente")))
A11: E010 | B11: Diagnóstico e estratégia | C11: Definir escopo e ordem das entregas | D11: Produto, UX e Liderança técnica | E11: E001, E005, E007, E008, E009 | F11: Plano de releases com critérios de saída | G11: Escopo preserva a jornada completa, explicita adiamentos e respeita dependências e capacidade. | H11: =COUNTIFS(Subetapas!A$2:A$1001,A11,Subetapas!G$2:G$1001,1) | I11: =IF(AND(N2="Concluída",N6="Concluída",N8="Concluída",N9="Concluída",N10="Concluída"),"Sim","Não") | M11: Não | N11: =IF(AND(H11=10,I11="Sim",LEN(TRIM(J11))>0,LEN(TRIM(K11))>0,LEN(TRIM(L11))>0,M11="Sim"),"Concluída",IF(H11=10,"Revisão ou dependências pendentes",IF(H11>0,"Em andamento","Pendente")))
A12: E011 | B12: Fundamentos e segurança | C12: Consolidar o modelo de dados do portal | D12: Backend e Arquitetura | E12: E003, E008, E010 | F12: Modelo canônico de entidades e contratos | G12: Nomes e vínculos de cooperativa, PA, verba e pedido são consistentes entre schema, serviços e telas. | H12: =COUNTIFS(Subetapas!A$2:A$1001,A12,Subetapas!G$2:G$1001,1) | I12: =IF(AND(N4="Concluída",N9="Concluída",N11="Concluída"),"Sim","Não") | M12: Não | N12: =IF(AND(H12=10,I12="Sim",LEN(TRIM(J12))>0,LEN(TRIM(K12))>0,LEN(TRIM(L12))>0,M12="Sim"),"Concluída",IF(H12=10,"Revisão ou dependências pendentes",IF(H12>0,"Em andamento","Pendente")))
A13: E012 | B13: Fundamentos e segurança | C13: Unificar permissões por ação e escopo | D13: Segurança e Backend | E13: E008, E011 | F13: Matriz de autorização implementável | G13: Permissões dependem de vínculo ativo e ação; cargo ou valor enviado pelo navegador não concedem acesso. | H13: =COUNTIFS(Subetapas!A$2:A$1001,A13,Subetapas!G$2:G$1001,1) | I13: =IF(AND(N9="Concluída",N12="Concluída"),"Sim","Não") | M13: Não | N13: =IF(AND(H13=10,I13="Sim",LEN(TRIM(J13))>0,LEN(TRIM(K13))>0,LEN(TRIM(L13))>0,M13="Sim"),"Concluída",IF(H13=10,"Revisão ou dependências pendentes",IF(H13>0,"Em andamento","Pendente")))
A14: E013 | B14: Fundamentos e segurança | C14: Implementar isolamento de dados e anexos | D14: Segurança e Backend | E14: E011, E012 | F14: Policies e testes entre organizações | G14: Usuários de cooperativas distintas não acessam registros, anexos ou funções fora de seu escopo. | H14: =COUNTIFS(Subetapas!A$2:A$1001,A14,Subetapas!G$2:G$1001,1) | I14: =IF(AND(N12="Concluída",N13="Concluída"),"Sim","Não") | M14: Não | N14: =IF(AND(H14=10,I14="Sim",LEN(TRIM(J14))>0,LEN(TRIM(K14))>0,LEN(TRIM(L14))>0,M14="Sim"),"Concluída",IF(H14=10,"Revisão ou dependências pendentes",IF(H14>0,"Em andamento","Pendente")))
A15: E014 | B15: Fundamentos e segurança | C15: Corrigir rotas e contrato de autenticação | D15: Frontend e QA | E15: E012, E013 | F15: Navegação autorizada por perfil | G15: Comprador, marketing e aprovador alcançam suas jornadas sem propriedades indefinidas ou barreiras contraditórias. | H15: =COUNTIFS(Subetapas!A$2:A$1001,A15,Subetapas!G$2:G$1001,1) | I15: =IF(AND(N13="Concluída",N14="Concluída"),"Sim","Não") | M15: Não | N15: =IF(AND(H15=10,I15="Sim",LEN(TRIM(J15))>0,LEN(TRIM(K15))>0,LEN(TRIM(L15))>0,M15="Sim"),"Concluída",IF(H15=10,"Revisão ou dependências pendentes",IF(H15>0,"Em andamento","Pendente")))
A16: E015 | B16: Fundamentos e segurança | C16: Definir autenticação confiável e acessível | D16: Segurança, Frontend e UX | E16: E002, E014 | F16: Fluxo técnico de entrada e recuperação | G16: Somente métodos realmente configurados aparecem; autenticação concluída corresponde a sessão válida. | H16: =COUNTIFS(Subetapas!A$2:A$1001,A16,Subetapas!G$2:G$1001,1) | I16: =IF(AND(N3="Concluída",N15="Concluída"),"Sim","Não") | M16: Não | N16: =IF(AND(H16=10,I16="Sim",LEN(TRIM(J16))>0,LEN(TRIM(K16))>0,LEN(TRIM(L16))>0,M16="Sim"),"Concluída",IF(H16=10,"Revisão ou dependências pendentes",IF(H16>0,"Em andamento","Pendente")))
A17: E016 | B17: Fundamentos e segurança | C17: Implementar convites e vínculos organizacionais | D17: Backend, UX e Administração | E17: E011, E012, E015 | F17: Onboarding controlado da cooperativa | G17: Convite cria apenas o vínculo autorizado; expiração, revogação e duplicidade possuem tratamento claro. | H17: =COUNTIFS(Subetapas!A$2:A$1001,A17,Subetapas!G$2:G$1001,1) | I17: =IF(AND(N12="Concluída",N13="Concluída",N16="Concluída"),"Sim","Não") | M17: Não | N17: =IF(AND(H17=10,I17="Sim",LEN(TRIM(J17))>0,LEN(TRIM(K17))>0,LEN(TRIM(L17))>0,M17="Sim"),"Concluída",IF(H17=10,"Revisão ou dependências pendentes",IF(H17>0,"Em andamento","Pendente")))
A18: E017 | B18: Fundamentos e segurança | C18: Tornar verba e compromissos consistentes | D18: Backend e Financeiro | E18: E008, E011, E012 | F18: Motor transacional de verba | G18: Concorrência e repetição não geram consumo duplicado nem saldo negativo fora da política autorizada. | H18: =COUNTIFS(Subetapas!A$2:A$1001,A18,Subetapas!G$2:G$1001,1) | I18: =IF(AND(N9="Concluída",N12="Concluída",N13="Concluída"),"Sim","Não") | M18: Não | N18: =IF(AND(H18=10,I18="Sim",LEN(TRIM(J18))>0,LEN(TRIM(K18))>0,LEN(TRIM(L18))>0,M18="Sim"),"Concluída",IF(H18=10,"Revisão ou dependências pendentes",IF(H18>0,"Em andamento","Pendente")))
A19: E018 | B19: Fundamentos e segurança | C19: Corrigir aprovação privilegiada no servidor | D19: Backend e Segurança | E19: E012, E013, E017 | F19: RPCs de decisão autorizadas e atômicas | G19: Ator, vínculo, alçada, versão e relação pedido/requisição são validados antes da decisão. | H19: =COUNTIFS(Subetapas!A$2:A$1001,A19,Subetapas!G$2:G$1001,1) | I19: =IF(AND(N13="Concluída",N14="Concluída",N18="Concluída"),"Sim","Não") | M19: Não | N19: =IF(AND(H19=10,I19="Sim",LEN(TRIM(J19))>0,LEN(TRIM(K19))>0,LEN(TRIM(L19))>0,M19="Sim"),"Concluída",IF(H19=10,"Revisão ou dependências pendentes",IF(H19>0,"Em andamento","Pendente")))
A20: E019 | B20: Fundamentos e segurança | C20: Restabelecer qualidade de build e testes | D20: Liderança técnica e QA | E20: E002, E003, E014, E018 | F20: Pipeline executável com resultados reais | G20: Gates críticos passam sem desativação; dívida remanescente possui inventário e não afeta a jornada liberada. | H20: =COUNTIFS(Subetapas!A$2:A$1001,A20,Subetapas!G$2:G$1001,1) | I20: =IF(AND(N3="Concluída",N4="Concluída",N15="Concluída",N19="Concluída"),"Sim","Não") | M20: Não | N20: =IF(AND(H20=10,I20="Sim",LEN(TRIM(J20))>0,LEN(TRIM(K20))>0,LEN(TRIM(L20))>0,M20="Sim"),"Concluída",IF(H20=10,"Revisão ou dependências pendentes",IF(H20>0,"Em andamento","Pendente")))
A21: E020 | B21: Fundamentos e segurança | C21: Preparar ambiente de validação e observabilidade | D21: Infraestrutura e Operação | E21: E001, E013, E019 | F21: Ambiente homologável e operação monitorada | G21: Saúde do catálogo e da compra pode ser observada; falhas têm alerta e responsável verificáveis. | H21: =COUNTIFS(Subetapas!A$2:A$1001,A21,Subetapas!G$2:G$1001,1) | I21: =IF(AND(N2="Concluída",N14="Concluída",N20="Concluída"),"Sim","Não") | M21: Não | N21: =IF(AND(H21=10,I21="Sim",LEN(TRIM(J21))>0,LEN(TRIM(K21))>0,LEN(TRIM(L21))>0,M21="Sim"),"Concluída",IF(H21=10,"Revisão ou dependências pendentes",IF(H21>0,"Em andamento","Pendente")))
A22: E021 | B22: Estrutura e conteúdo | C22: Organizar a arquitetura de informação | D22: UX e Conteúdo | E22: E005, E006, E010 | F22: Mapa de navegação por tarefa | G22: Participantes encontram catálogo, solicitações, aprovações e entregas sem depender de termos de vendedor. | H22: =COUNTIFS(Subetapas!A$2:A$1001,A22,Subetapas!G$2:G$1001,1) | I22: =IF(AND(N6="Concluída",N7="Concluída",N11="Concluída"),"Sim","Não") | M22: Não | N22: =IF(AND(H22=10,I22="Sim",LEN(TRIM(J22))>0,LEN(TRIM(K22))>0,LEN(TRIM(L22))>0,M22="Sim"),"Concluída",IF(H22=10,"Revisão ou dependências pendentes",IF(H22>0,"Em andamento","Pendente")))
A23: E022 | B23: Estrutura e conteúdo | C23: Construir taxonomia útil para brindes | D23: UX, Comercial e Dados | E23: E003, E005, E021 | F23: Taxonomia e mapeamento de atributos | G23: Categorias e atributos ajudam a decidir; valores desconhecidos não são apresentados como fatos. | H23: =COUNTIFS(Subetapas!A$2:A$1001,A23,Subetapas!G$2:G$1001,1) | I23: =IF(AND(N4="Concluída",N6="Concluída",N22="Concluída"),"Sim","Não") | M23: Não | N23: =IF(AND(H23=10,I23="Sim",LEN(TRIM(J23))>0,LEN(TRIM(K23))>0,LEN(TRIM(L23))>0,M23="Sim"),"Concluída",IF(H23=10,"Revisão ou dependências pendentes",IF(H23>0,"Em andamento","Pendente")))
A24: E023 | B24: Estrutura e conteúdo | C24: Projetar o comportamento da busca | D24: UX e Engenharia de busca | E24: E021, E022 | F24: Especificação de busca por nome, código e intenção | G24: Consultas prioritárias retornam opções pertinentes ou recuperação clara, sem inventar atributos. | H24: =COUNTIFS(Subetapas!A$2:A$1001,A24,Subetapas!G$2:G$1001,1) | I24: =IF(AND(N22="Concluída",N23="Concluída"),"Sim","Não") | M24: Não | N24: =IF(AND(H24=10,I24="Sim",LEN(TRIM(J24))>0,LEN(TRIM(K24))>0,LEN(TRIM(L24))>0,M24="Sim"),"Concluída",IF(H24=10,"Revisão ou dependências pendentes",IF(H24>0,"Em andamento","Pendente")))
A25: E024 | B25: Estrutura e conteúdo | C25: Projetar filtros e ordenação | D25: UX e Comercial | E25: E022, E023 | F25: Modelo de refinamento e ordenação | G25: Comprador entende critérios ativos, remove restrições e compara resultados sem perder contexto. | H25: =COUNTIFS(Subetapas!A$2:A$1001,A25,Subetapas!G$2:G$1001,1) | I25: =IF(AND(N23="Concluída",N24="Concluída"),"Sim","Não") | M25: Não | N25: =IF(AND(H25=10,I25="Sim",LEN(TRIM(J25))>0,LEN(TRIM(K25))>0,LEN(TRIM(L25))>0,M25="Sim"),"Concluída",IF(H25=10,"Revisão ou dependências pendentes",IF(H25>0,"Em andamento","Pendente")))
A26: E025 | B26: Estrutura e conteúdo | C26: Desenhar navegação entre cooperativas e unidades | D26: UX, Segurança e Frontend | E26: E012, E014, E016, E021 | F26: Padrão de contexto organizacional | G26: A unidade ativa é inequívoca; trocar contexto não transporta dados privados ou rascunhos incorretos. | H26: =COUNTIFS(Subetapas!A$2:A$1001,A26,Subetapas!G$2:G$1001,1) | I26: =IF(AND(N13="Concluída",N15="Concluída",N17="Concluída",N22="Concluída"),"Sim","Não") | M26: Não | N26: =IF(AND(H26=10,I26="Sim",LEN(TRIM(J26))>0,LEN(TRIM(K26))>0,LEN(TRIM(L26))>0,M26="Sim"),"Concluída",IF(H26=10,"Revisão ou dependências pendentes",IF(H26>0,"Em andamento","Pendente")))
A27: E026 | B27: Estrutura e conteúdo | C27: Estabelecer linguagem e conteúdo de interface | D27: Conteúdo UX e Produto | E27: E005, E008, E021 | F27: Guia de linguagem aplicado às jornadas | G27: Textos distinguem estimativa, aprovação, contratação e entrega sem promessas não comprovadas. | H27: =COUNTIFS(Subetapas!A$2:A$1001,A27,Subetapas!G$2:G$1001,1) | I27: =IF(AND(N6="Concluída",N9="Concluída",N22="Concluída"),"Sim","Não") | M27: Não | N27: =IF(AND(H27=10,I27="Sim",LEN(TRIM(J27))>0,LEN(TRIM(K27))>0,LEN(TRIM(L27))>0,M27="Sim"),"Concluída",IF(H27=10,"Revisão ou dependências pendentes",IF(H27>0,"Em andamento","Pendente")))
A28: E027 | B28: Estrutura e conteúdo | C28: Padronizar formulários e entrada de dados | D28: UX, Conteúdo e Frontend | E28: E011, E021, E026 | F28: Padrões de formulários com validação útil | G28: Campos solicitam apenas dados necessários; erros preservam valores e orientam correção. | H28: =COUNTIFS(Subetapas!A$2:A$1001,A28,Subetapas!G$2:G$1001,1) | I28: =IF(AND(N12="Concluída",N22="Concluída",N27="Concluída"),"Sim","Não") | M28: Não | N28: =IF(AND(H28=10,I28="Sim",LEN(TRIM(J28))>0,LEN(TRIM(K28))>0,LEN(TRIM(L28))>0,M28="Sim"),"Concluída",IF(H28=10,"Revisão ou dependências pendentes",IF(H28>0,"Em andamento","Pendente")))
A29: E028 | B29: Estrutura e conteúdo | C29: Definir estados vazios, falhas e recuperação | D29: UX, Frontend e Backend | E29: E003, E014, E026, E027 | F29: Catálogo de estados com comportamento real | G29: Cada falha oferece uma ação segura; carregamento e ausência de dados não ocultam indisponibilidade. | H29: =COUNTIFS(Subetapas!A$2:A$1001,A29,Subetapas!G$2:G$1001,1) | I29: =IF(AND(N4="Concluída",N15="Concluída",N27="Concluída",N28="Concluída"),"Sim","Não") | M29: Não | N29: =IF(AND(H29=10,I29="Sim",LEN(TRIM(J29))>0,LEN(TRIM(K29))>0,LEN(TRIM(L29))>0,M29="Sim"),"Concluída",IF(H29=10,"Revisão ou dependências pendentes",IF(H29>0,"Em andamento","Pendente")))
A30: E029 | B30: Estrutura e conteúdo | C30: Planejar avisos e notificações por evento | D30: UX, Operação e Backend | E30: E007, E009, E012, E026 | F30: Matriz de eventos, destinatários e canais | G30: Avisos têm destinatário autorizado e próxima ação; canal inexistente não é anunciado. | H30: =COUNTIFS(Subetapas!A$2:A$1001,A30,Subetapas!G$2:G$1001,1) | I30: =IF(AND(N8="Concluída",N10="Concluída",N13="Concluída",N27="Concluída"),"Sim","Não") | M30: Não | N30: =IF(AND(H30=10,I30="Sim",LEN(TRIM(J30))>0,LEN(TRIM(K30))>0,LEN(TRIM(L30))>0,M30="Sim"),"Concluída",IF(H30=10,"Revisão ou dependências pendentes",IF(H30>0,"Em andamento","Pendente")))
A31: E030 | B31: Estrutura e conteúdo | C31: Validar fluxos em protótipos de baixa fidelidade | D31: UX e Pesquisa | E31: E021, E023, E024, E025, E027, E028, E029 | F31: Fluxos testados antes do acabamento visual | G31: Tarefas críticas são compreendidas; problemas graves têm correção e nova verificação. | H31: =COUNTIFS(Subetapas!A$2:A$1001,A31,Subetapas!G$2:G$1001,1) | I31: =IF(AND(N22="Concluída",N24="Concluída",N25="Concluída",N26="Concluída",N28="Concluída",N29="Concluída",N30="Concluída"),"Sim","Não") | M31: Não | N31: =IF(AND(H31=10,I31="Sim",LEN(TRIM(J31))>0,LEN(TRIM(K31))>0,LEN(TRIM(L31))>0,M31="Sim"),"Concluída",IF(H31=10,"Revisão ou dependências pendentes",IF(H31>0,"Em andamento","Pendente")))
A32: E031 | B32: Sistema visual | C32: Definir direção visual com a marca Sicoob | D32: Direção de design e responsável pela marca | E32: E010, E026, E030 | F32: Direção visual e ativos autorizados | G32: A proposta usa a versão de marca validada e demonstra consistência em telas reais do portal. | H32: =COUNTIFS(Subetapas!A$2:A$1001,A32,Subetapas!G$2:G$1001,1) | I32: =IF(AND(N11="Concluída",N27="Concluída",N31="Concluída"),"Sim","Não") | M32: Não | N32: =IF(AND(H32=10,I32="Sim",LEN(TRIM(J32))>0,LEN(TRIM(K32))>0,LEN(TRIM(L32))>0,M32="Sim"),"Concluída",IF(H32=10,"Revisão ou dependências pendentes",IF(H32>0,"Em andamento","Pendente")))
A33: E032 | B33: Sistema visual | C33: Estabelecer grade, espaçamento e densidade | D33: Design de interface e Frontend | E33: E030, E031 | F33: Sistema de layout responsivo | G33: Páginas mantêm hierarquia e leitura em larguras pequenas, médias e amplas, sem medidas arbitrárias por tela. | H33: =COUNTIFS(Subetapas!A$2:A$1001,A33,Subetapas!G$2:G$1001,1) | I33: =IF(AND(N31="Concluída",N32="Concluída"),"Sim","Não") | M33: Não | N33: =IF(AND(H33=10,I33="Sim",LEN(TRIM(J33))>0,LEN(TRIM(K33))>0,LEN(TRIM(L33))>0,M33="Sim"),"Concluída",IF(H33=10,"Revisão ou dependências pendentes",IF(H33>0,"Em andamento","Pendente")))
A34: E033 | B34: Sistema visual | C34: Definir tipografia e hierarquia de leitura | D34: Design de interface e Conteúdo | E34: E026, E031, E032 | F34: Escala tipográfica aplicada | G34: Textos, valores e estados são legíveis; carregamento de fontes não prejudica a tarefa. | H34: =COUNTIFS(Subetapas!A$2:A$1001,A34,Subetapas!G$2:G$1001,1) | I34: =IF(AND(N27="Concluída",N32="Concluída",N33="Concluída"),"Sim","Não") | M34: Não | N34: =IF(AND(H34=10,I34="Sim",LEN(TRIM(J34))>0,LEN(TRIM(K34))>0,LEN(TRIM(L34))>0,M34="Sim"),"Concluída",IF(H34=10,"Revisão ou dependências pendentes",IF(H34>0,"Em andamento","Pendente")))
A35: E034 | B35: Sistema visual | C35: Definir cores semânticas e contraste | D35: Design de interface e Acessibilidade | E35: E031, E033 | F35: Paleta semântica acessível | G35: Combinações de texto e controles atendem os critérios aplicáveis; estado nunca depende apenas de cor. | H35: =COUNTIFS(Subetapas!A$2:A$1001,A35,Subetapas!G$2:G$1001,1) | I35: =IF(AND(N32="Concluída",N34="Concluída"),"Sim","Não") | M35: Não | N35: =IF(AND(H35=10,I35="Sim",LEN(TRIM(J35))>0,LEN(TRIM(K35))>0,LEN(TRIM(L35))>0,M35="Sim"),"Concluída",IF(H35=10,"Revisão ou dependências pendentes",IF(H35>0,"Em andamento","Pendente")))
A36: E035 | B36: Sistema visual | C36: Padronizar imagens, ícones e representação de produto | D36: Design e Conteúdo de catálogo | E36: E022, E031, E034 | F36: Guia de ativos visuais comerciais | G36: Imagens ajudam a avaliar o produto e distinguem fotografia, simulação e prova de produção. | H36: =COUNTIFS(Subetapas!A$2:A$1001,A36,Subetapas!G$2:G$1001,1) | I36: =IF(AND(N23="Concluída",N32="Concluída",N35="Concluída"),"Sim","Não") | M36: Não | N36: =IF(AND(H36=10,I36="Sim",LEN(TRIM(J36))>0,LEN(TRIM(K36))>0,LEN(TRIM(L36))>0,M36="Sim"),"Concluída",IF(H36=10,"Revisão ou dependências pendentes",IF(H36>0,"Em andamento","Pendente")))
A37: E036 | B37: Sistema visual | C37: Implementar tokens de design | D37: Frontend e Design de sistemas | E37: E032, E033, E034, E035 | F37: Tokens compartilhados entre especificação e código | G37: Mudança de um token atualiza os componentes correspondentes sem divergência visual ou semântica. | H37: =COUNTIFS(Subetapas!A$2:A$1001,A37,Subetapas!G$2:G$1001,1) | I37: =IF(AND(N33="Concluída",N34="Concluída",N35="Concluída",N36="Concluída"),"Sim","Não") | M37: Não | N37: =IF(AND(H37=10,I37="Sim",LEN(TRIM(J37))>0,LEN(TRIM(K37))>0,LEN(TRIM(L37))>0,M37="Sim"),"Concluída",IF(H37=10,"Revisão ou dependências pendentes",IF(H37>0,"Em andamento","Pendente")))
A38: E037 | B38: Sistema visual | C38: Consolidar componentes de ação e formulário | D38: Frontend, Design e Acessibilidade | E38: E027, E028, E036 | F38: Biblioteca essencial de interação | G38: Componentes possuem estados, semântica, foco e mensagens consistentes nas jornadas críticas. | H38: =COUNTIFS(Subetapas!A$2:A$1001,A38,Subetapas!G$2:G$1001,1) | I38: =IF(AND(N28="Concluída",N29="Concluída",N37="Concluída"),"Sim","Não") | M38: Não | N38: =IF(AND(H38=10,I38="Sim",LEN(TRIM(J38))>0,LEN(TRIM(K38))>0,LEN(TRIM(L38))>0,M38="Sim"),"Concluída",IF(H38=10,"Revisão ou dependências pendentes",IF(H38>0,"Em andamento","Pendente")))
A39: E038 | B39: Sistema visual | C39: Consolidar tabelas, listas e visualização de estados | D39: Frontend e Design | E39: E032, E033, E034, E036 | F39: Componentes de consulta operacional | G39: Dados densos continuam legíveis e operáveis, com seleção e paginação inequívocas. | H39: =COUNTIFS(Subetapas!A$2:A$1001,A39,Subetapas!G$2:G$1001,1) | I39: =IF(AND(N33="Concluída",N34="Concluída",N35="Concluída",N37="Concluída"),"Sim","Não") | M39: Não | N39: =IF(AND(H39=10,I39="Sim",LEN(TRIM(J39))>0,LEN(TRIM(K39))>0,LEN(TRIM(L39))>0,M39="Sim"),"Concluída",IF(H39=10,"Revisão ou dependências pendentes",IF(H39>0,"Em andamento","Pendente")))
A40: E039 | B40: Sistema visual | C40: Projetar feedback e movimento com propósito | D40: Design de interação e Frontend | E40: E028, E036, E037, E038 | F40: Padrão de transições e feedback | G40: Movimento orienta a tarefa, respeita redução de animação e não encobre confirmação operacional. | H40: =COUNTIFS(Subetapas!A$2:A$1001,A40,Subetapas!G$2:G$1001,1) | I40: =IF(AND(N29="Concluída",N37="Concluída",N38="Concluída",N39="Concluída"),"Sim","Não") | M40: Não | N40: =IF(AND(H40=10,I40="Sim",LEN(TRIM(J40))>0,LEN(TRIM(K40))>0,LEN(TRIM(L40))>0,M40="Sim"),"Concluída",IF(H40=10,"Revisão ou dependências pendentes",IF(H40>0,"Em andamento","Pendente")))
A41: E040 | B41: Sistema visual | C41: Governar o sistema de design | D41: Design de sistemas e Liderança técnica | E41: E036, E037, E038, E039 | F41: Catálogo de componentes e processo de evolução | G41: As páginas novas usam componentes publicados; exceções possuem justificativa e responsável. | H41: =COUNTIFS(Subetapas!A$2:A$1001,A41,Subetapas!G$2:G$1001,1) | I41: =IF(AND(N37="Concluída",N38="Concluída",N39="Concluída",N40="Concluída"),"Sim","Não") | M41: Não | N41: =IF(AND(H41=10,I41="Sim",LEN(TRIM(J41))>0,LEN(TRIM(K41))>0,LEN(TRIM(L41))>0,M41="Sim"),"Concluída",IF(H41=10,"Revisão ou dependências pendentes",IF(H41>0,"Em andamento","Pendente")))
A42: E041 | B42: Catálogo e decisão | C42: Redesenhar a experiência de acesso | D42: UX, Frontend e Conteúdo | E42: E015, E016, E026, E040 | F42: Login e recuperação prontos para uso institucional | G42: Usuário identifica o serviço, entra ou recupera acesso sem controles de teste ou provedores fictícios. | H42: =COUNTIFS(Subetapas!A$2:A$1001,A42,Subetapas!G$2:G$1001,1) | I42: =IF(AND(N16="Concluída",N17="Concluída",N27="Concluída",N41="Concluída"),"Sim","Não") | M42: Não | N42: =IF(AND(H42=10,I42="Sim",LEN(TRIM(J42))>0,LEN(TRIM(K42))>0,LEN(TRIM(L42))>0,M42="Sim"),"Concluída",IF(H42=10,"Revisão ou dependências pendentes",IF(H42>0,"Em andamento","Pendente")))
A43: E042 | B43: Catálogo e decisão | C43: Criar início orientado às pendências | D43: UX, Frontend e Produto | E43: E009, E025, E029, E038, E040, E041 | F43: Página inicial por responsabilidade | G43: As informações apresentadas correspondem ao contexto ativo e levam diretamente à próxima ação útil. | H43: =COUNTIFS(Subetapas!A$2:A$1001,A43,Subetapas!G$2:G$1001,1) | I43: =IF(AND(N10="Concluída",N26="Concluída",N30="Concluída",N39="Concluída",N41="Concluída",N42="Concluída"),"Sim","Não") | M43: Não | N43: =IF(AND(H43=10,I43="Sim",LEN(TRIM(J43))>0,LEN(TRIM(K43))>0,LEN(TRIM(L43))>0,M43="Sim"),"Concluída",IF(H43=10,"Revisão ou dependências pendentes",IF(H43>0,"Em andamento","Pendente")))
A44: E043 | B44: Catálogo e decisão | C44: Implementar listagem de catálogo útil | D44: Frontend, UX e Catálogo | E44: E003, E022, E024, E035, E038, E040 | F44: Catálogo responsivo conectado | G44: Itens exibem dados reais, variante identificável e condições suficientes para iniciar uma seleção. | H44: =COUNTIFS(Subetapas!A$2:A$1001,A44,Subetapas!G$2:G$1001,1) | I44: =IF(AND(N4="Concluída",N23="Concluída",N25="Concluída",N36="Concluída",N39="Concluída",N41="Concluída"),"Sim","Não") | M44: Não | N44: =IF(AND(H44=10,I44="Sim",LEN(TRIM(J44))>0,LEN(TRIM(K44))>0,LEN(TRIM(L44))>0,M44="Sim"),"Concluída",IF(H44=10,"Revisão ou dependências pendentes",IF(H44>0,"Em andamento","Pendente")))
A45: E044 | B45: Catálogo e decisão | C45: Implementar busca com recuperação de intenção | D45: Frontend e Engenharia de busca | E45: E023, E028, E037, E043 | F45: Busca operacional e mensurável | G45: Consultas prioritárias encontram itens esperados; ausência ou erro oferece recuperação coerente. | H45: =COUNTIFS(Subetapas!A$2:A$1001,A45,Subetapas!G$2:G$1001,1) | I45: =IF(AND(N24="Concluída",N29="Concluída",N38="Concluída",N44="Concluída"),"Sim","Não") | M45: Não | N45: =IF(AND(H45=10,I45="Sim",LEN(TRIM(J45))>0,LEN(TRIM(K45))>0,LEN(TRIM(L45))>0,M45="Sim"),"Concluída",IF(H45=10,"Revisão ou dependências pendentes",IF(H45>0,"Em andamento","Pendente")))
A46: E045 | B46: Catálogo e decisão | C46: Implementar filtros acessíveis e persistentes | D46: Frontend e UX | E46: E024, E037, E043, E044 | F46: Refinamento de catálogo por critérios reais | G46: Filtros ativos são visíveis, reversíveis e preservados ao navegar, inclusive em tela móvel. | H46: =COUNTIFS(Subetapas!A$2:A$1001,A46,Subetapas!G$2:G$1001,1) | I46: =IF(AND(N25="Concluída",N38="Concluída",N44="Concluída",N45="Concluída"),"Sim","Não") | M46: Não | N46: =IF(AND(H46=10,I46="Sim",LEN(TRIM(J46))>0,LEN(TRIM(K46))>0,LEN(TRIM(L46))>0,M46="Sim"),"Concluída",IF(H46=10,"Revisão ou dependências pendentes",IF(H46>0,"Em andamento","Pendente")))
A47: E046 | B47: Catálogo e decisão | C47: Construir página de produto para decisão | D47: UX, Catálogo e Frontend | E47: E019, E035, E040, E043, E045 | F47: Detalhe comercial e técnico do produto | G47: Comprador entende o item, suas restrições e o próximo passo sem confundir simulação com contratação. | H47: =COUNTIFS(Subetapas!A$2:A$1001,A47,Subetapas!G$2:G$1001,1) | I47: =IF(AND(N20="Concluída",N36="Concluída",N41="Concluída",N44="Concluída",N46="Concluída"),"Sim","Não") | M47: Não | N47: =IF(AND(H47=10,I47="Sim",LEN(TRIM(J47))>0,LEN(TRIM(K47))>0,LEN(TRIM(L47))>0,M47="Sim"),"Concluída",IF(H47=10,"Revisão ou dependências pendentes",IF(H47>0,"Em andamento","Pendente")))
A48: E047 | B48: Catálogo e decisão | C48: Especificar personalização sem ambiguidade | D48: UX, Produção e Frontend | E48: E007, E035, E037, E046 | F48: Configurador de personalização comercialmente válido | G48: Técnica, área, dimensão e quantidade de cores formam uma configuração executável ou exigem análise explícita. | H48: =COUNTIFS(Subetapas!A$2:A$1001,A48,Subetapas!G$2:G$1001,1) | I48: =IF(AND(N8="Concluída",N36="Concluída",N38="Concluída",N47="Concluída"),"Sim","Não") | M48: Não | N48: =IF(AND(H48=10,I48="Sim",LEN(TRIM(J48))>0,LEN(TRIM(K48))>0,LEN(TRIM(L48))>0,M48="Sim"),"Concluída",IF(H48=10,"Revisão ou dependências pendentes",IF(H48>0,"Em andamento","Pendente")))
A49: E048 | B49: Catálogo e decisão | C49: Implementar simulação transparente de custo e prazo | D49: Comercial, UX e Backend | E49: E003, E017, E019, E046, E047 | F49: Simulador com condições explícitas | G49: Total e prazo exibidos são reproduzíveis; estimativa não é apresentada como proposta firme ou reserva. | H49: =COUNTIFS(Subetapas!A$2:A$1001,A49,Subetapas!G$2:G$1001,1) | I49: =IF(AND(N4="Concluída",N18="Concluída",N20="Concluída",N47="Concluída",N48="Concluída"),"Sim","Não") | M49: Não | N49: =IF(AND(H49=10,I49="Sim",LEN(TRIM(J49))>0,LEN(TRIM(K49))>0,LEN(TRIM(L49))>0,M49="Sim"),"Concluída",IF(H49=10,"Revisão ou dependências pendentes",IF(H49>0,"Em andamento","Pendente")))
A50: E049 | B50: Catálogo e decisão | C50: Implementar comparação de alternativas | D50: UX, Frontend e Compras | E50: E038, E046, E048 | F50: Comparador de propostas de produto | G50: Comparação usa quantidades e bases equivalentes e evidencia informações desconhecidas. | H50: =COUNTIFS(Subetapas!A$2:A$1001,A50,Subetapas!G$2:G$1001,1) | I50: =IF(AND(N39="Concluída",N47="Concluída",N49="Concluída"),"Sim","Não") | M50: Não | N50: =IF(AND(H50=10,I50="Sim",LEN(TRIM(J50))>0,LEN(TRIM(K50))>0,LEN(TRIM(L50))>0,M50="Sim"),"Concluída",IF(H50=10,"Revisão ou dependências pendentes",IF(H50>0,"Em andamento","Pendente")))
A51: E050 | B51: Catálogo e decisão | C51: Organizar favoritos e coleções compartilhadas | D51: UX, Frontend e Segurança | E51: E013, E025, E043, E046, E049 | F51: Coleções privadas e colaboração autorizada | G51: Pessoas compartilham seleções no escopo permitido sem publicar custos internos ou dados de outra cooperativa. | H51: =COUNTIFS(Subetapas!A$2:A$1001,A51,Subetapas!G$2:G$1001,1) | I51: =IF(AND(N14="Concluída",N26="Concluída",N44="Concluída",N47="Concluída",N50="Concluída"),"Sim","Não") | M51: Não | N51: =IF(AND(H51=10,I51="Sim",LEN(TRIM(J51))>0,LEN(TRIM(K51))>0,LEN(TRIM(L51))>0,M51="Sim"),"Concluída",IF(H51=10,"Revisão ou dependências pendentes",IF(H51>0,"Em andamento","Pendente")))
A52: E051 | B52: Campanhas e propostas | C52: Criar briefing de campanha e necessidade | D52: UX, Marketing e Produto | E52: E008, E027, E030, E040, E050 | F52: Formulário de campanha com contexto suficiente | G52: Briefing orienta seleção e operação sem exigir informações que o solicitante ainda não possui. | H52: =COUNTIFS(Subetapas!A$2:A$1001,A52,Subetapas!G$2:G$1001,1) | I52: =IF(AND(N9="Concluída",N28="Concluída",N31="Concluída",N41="Concluída",N51="Concluída"),"Sim","Não") | M52: Não | N52: =IF(AND(H52=10,I52="Sim",LEN(TRIM(J52))>0,LEN(TRIM(K52))>0,LEN(TRIM(L52))>0,M52="Sim"),"Concluída",IF(H52=10,"Revisão ou dependências pendentes",IF(H52>0,"Em andamento","Pendente")))
A53: E052 | B53: Campanhas e propostas | C53: Planejar campanhas e marcos de prazo | D53: Marketing, UX e Operação | E53: E007, E029, E048, E051 | F53: Visão de campanhas com dependências de prazo | G53: Agenda separa datas confirmadas de estimadas e evidencia risco de não atender ao evento. | H53: =COUNTIFS(Subetapas!A$2:A$1001,A53,Subetapas!G$2:G$1001,1) | I53: =IF(AND(N8="Concluída",N30="Concluída",N49="Concluída",N52="Concluída"),"Sim","Não") | M53: Não | N53: =IF(AND(H53=10,I53="Sim",LEN(TRIM(J53))>0,LEN(TRIM(K53))>0,LEN(TRIM(L53))>0,M53="Sim"),"Concluída",IF(H53=10,"Revisão ou dependências pendentes",IF(H53>0,"Em andamento","Pendente")))
A54: E053 | B54: Campanhas e propostas | C54: Organizar biblioteca de marcas e arquivos | D54: Design, Marketing e Segurança | E54: E013, E016, E031, E051 | F54: Biblioteca privada de ativos por cooperativa | G54: Arquivos têm proprietário, versão e permissão; um ativo de outra cooperativa não pode ser aplicado indevidamente. | H54: =COUNTIFS(Subetapas!A$2:A$1001,A54,Subetapas!G$2:G$1001,1) | I54: =IF(AND(N14="Concluída",N17="Concluída",N32="Concluída",N52="Concluída"),"Sim","Não") | M54: Não | N54: =IF(AND(H54=10,I54="Sim",LEN(TRIM(J54))>0,LEN(TRIM(K54))>0,LEN(TRIM(L54))>0,M54="Sim"),"Concluída",IF(H54=10,"Revisão ou dependências pendentes",IF(H54>0,"Em andamento","Pendente")))
A55: E054 | B55: Campanhas e propostas | C55: Produzir prova técnica da personalização | D55: Produção, Design e Frontend | E55: E047, E051, E053 | F55: Prova técnica versionada por item | G55: Documento identifica produto, variante, técnica, dimensões e arquivo exato proposto para produção. | H55: =COUNTIFS(Subetapas!A$2:A$1001,A55,Subetapas!G$2:G$1001,1) | I55: =IF(AND(N48="Concluída",N52="Concluída",N54="Concluída"),"Sim","Não") | M55: Não | N55: =IF(AND(H55=10,I55="Sim",LEN(TRIM(J55))>0,LEN(TRIM(K55))>0,LEN(TRIM(L55))>0,M55="Sim"),"Concluída",IF(H55=10,"Revisão ou dependências pendentes",IF(H55>0,"Em andamento","Pendente")))
A56: E055 | B56: Campanhas e propostas | C56: Construir kits com composição verificável | D56: UX, Comercial e Frontend | E56: E046, E047, E048, E051 | F56: Montador de kits com custo e restrições | G56: Composição respeita quantidades, mínimos, disponibilidade e embalagem; preço pode ser reproduzido por item. | H56: =COUNTIFS(Subetapas!A$2:A$1001,A56,Subetapas!G$2:G$1001,1) | I56: =IF(AND(N47="Concluída",N48="Concluída",N49="Concluída",N52="Concluída"),"Sim","Não") | M56: Não | N56: =IF(AND(H56=10,I56="Sim",LEN(TRIM(J56))>0,LEN(TRIM(K56))>0,LEN(TRIM(L56))>0,M56="Sim"),"Concluída",IF(H56=10,"Revisão ou dependências pendentes",IF(H56>0,"Em andamento","Pendente")))
A57: E056 | B57: Campanhas e propostas | C57: Planejar distribuição por PA e destino | D57: UX, Compras e Operação | E57: E011, E025, E027, E048, E051, E055 | F57: Distribuição de quantidades e custos por destino | G57: A soma distribuída confere com o total; cada destino tem identificação, prazo e vínculo autorizado. | H57: =COUNTIFS(Subetapas!A$2:A$1001,A57,Subetapas!G$2:G$1001,1) | I57: =IF(AND(N12="Concluída",N26="Concluída",N28="Concluída",N49="Concluída",N52="Concluída",N56="Concluída"),"Sim","Não") | M57: Não | N57: =IF(AND(H57=10,I57="Sim",LEN(TRIM(J57))>0,LEN(TRIM(K57))>0,LEN(TRIM(L57))>0,M57="Sim"),"Concluída",IF(H57=10,"Revisão ou dependências pendentes",IF(H57>0,"Em andamento","Pendente")))
A58: E057 | B58: Campanhas e propostas | C58: Criar carrinho de solicitação institucional | D58: UX e Frontend | E58: E025, E046, E048, E050, E055, E056 | F58: Carrinho vinculado ao contexto correto | G58: Itens, configurações e destinos persistem corretamente; alterações relevantes exigem recalcular a proposta. | H58: =COUNTIFS(Subetapas!A$2:A$1001,A58,Subetapas!G$2:G$1001,1) | I58: =IF(AND(N26="Concluída",N47="Concluída",N49="Concluída",N51="Concluída",N56="Concluída",N57="Concluída"),"Sim","Não") | M58: Não | N58: =IF(AND(H58=10,I58="Sim",LEN(TRIM(J58))>0,LEN(TRIM(K58))>0,LEN(TRIM(L58))>0,M58="Sim"),"Concluída",IF(H58=10,"Revisão ou dependências pendentes",IF(H58>0,"Em andamento","Pendente")))
A59: E058 | B59: Campanhas e propostas | C59: Apresentar orçamento com custo total claro | D59: UX, Comercial e Frontend | E59: E026, E048, E056, E057 | F59: Resumo comercial completo e compreensível | G59: A soma de itens e encargos coincide com o total; não há custo obrigatório oculto no avanço. | H59: =COUNTIFS(Subetapas!A$2:A$1001,A59,Subetapas!G$2:G$1001,1) | I59: =IF(AND(N27="Concluída",N49="Concluída",N57="Concluída",N58="Concluída"),"Sim","Não") | M59: Não | N59: =IF(AND(H59=10,I59="Sim",LEN(TRIM(J59))>0,LEN(TRIM(K59))>0,LEN(TRIM(L59))>0,M59="Sim"),"Concluída",IF(H59=10,"Revisão ou dependências pendentes",IF(H59>0,"Em andamento","Pendente")))
A60: E059 | B60: Campanhas e propostas | C60: Versionar propostas e preservar decisões | D60: Backend, Comercial e UX | E60: E011, E018, E054, E058 | F60: Proposta versionada com histórico imutável | G60: Pedido e aprovações referenciam a versão exata; atualização de catálogo não reescreve o histórico. | H60: =COUNTIFS(Subetapas!A$2:A$1001,A60,Subetapas!G$2:G$1001,1) | I60: =IF(AND(N12="Concluída",N19="Concluída",N55="Concluída",N59="Concluída"),"Sim","Não") | M60: Não | N60: =IF(AND(H60=10,I60="Sim",LEN(TRIM(J60))>0,LEN(TRIM(K60))>0,LEN(TRIM(L60))>0,M60="Sim"),"Concluída",IF(H60=10,"Revisão ou dependências pendentes",IF(H60>0,"Em andamento","Pendente")))
A61: E060 | B61: Campanhas e propostas | C61: Comparar cotações e justificar a escolha | D61: Compras, UX e Backend | E61: E008, E049, E058, E059 | F61: Comparação comercial conforme política local | G61: Escolha considera bases equivalentes e reúne evidências exigidas pela cooperativa, incluindo exceções. | H61: =COUNTIFS(Subetapas!A$2:A$1001,A61,Subetapas!G$2:G$1001,1) | I61: =IF(AND(N9="Concluída",N50="Concluída",N59="Concluída",N60="Concluída"),"Sim","Não") | M61: Não | N61: =IF(AND(H61=10,I61="Sim",LEN(TRIM(J61))>0,LEN(TRIM(K61))>0,LEN(TRIM(L61))>0,M61="Sim"),"Concluída",IF(H61=10,"Revisão ou dependências pendentes",IF(H61>0,"Em andamento","Pendente")))
A62: E061 | B62: Governança e aprovações | C62: Formalizar a solicitação de compra | D62: UX, Frontend e Backend | E62: E008, E017, E018, E057, E059, E060 | F62: Solicitação completa e rastreável | G62: Envio registra contexto, versão, justificativa e destinatário; repetição não cria solicitações duplicadas. | H62: =COUNTIFS(Subetapas!A$2:A$1001,A62,Subetapas!G$2:G$1001,1) | I62: =IF(AND(N9="Concluída",N18="Concluída",N19="Concluída",N58="Concluída",N60="Concluída",N61="Concluída"),"Sim","Não") | M62: Não | N62: =IF(AND(H62=10,I62="Sim",LEN(TRIM(J62))>0,LEN(TRIM(K62))>0,LEN(TRIM(L62))>0,M62="Sim"),"Concluída",IF(H62=10,"Revisão ou dependências pendentes",IF(H62>0,"Em andamento","Pendente")))
A63: E062 | B63: Governança e aprovações | C63: Construir a experiência de verba e saldo | D63: UX, Financeiro e Frontend | E63: E017, E025, E033, E038, E042, E061 | F63: Carteira de verba compreensível | G63: Saldo, período e movimentos conciliam com o contrato financeiro; nenhum número fixo substitui dados reais. | H63: =COUNTIFS(Subetapas!A$2:A$1001,A63,Subetapas!G$2:G$1001,1) | I63: =IF(AND(N18="Concluída",N26="Concluída",N34="Concluída",N39="Concluída",N43="Concluída",N62="Concluída"),"Sim","Não") | M63: Não | N63: =IF(AND(H63=10,I63="Sim",LEN(TRIM(J63))>0,LEN(TRIM(K63))>0,LEN(TRIM(L63))>0,M63="Sim"),"Concluída",IF(H63=10,"Revisão ou dependências pendentes",IF(H63>0,"Em andamento","Pendente")))
A64: E063 | B64: Governança e aprovações | C64: Criar fila de aprovações orientada a decisão | D64: UX, Compras e Frontend | E64: E012, E029, E038, E059, E061, E062 | F64: Fila de decisões com contexto e prioridade | G64: Aprovador identifica pendência, versão e risco de prazo sem abrir várias telas para obter dados básicos. | H64: =COUNTIFS(Subetapas!A$2:A$1001,A64,Subetapas!G$2:G$1001,1) | I64: =IF(AND(N13="Concluída",N30="Concluída",N39="Concluída",N60="Concluída",N62="Concluída",N63="Concluída"),"Sim","Não") | M64: Não | N64: =IF(AND(H64=10,I64="Sim",LEN(TRIM(J64))>0,LEN(TRIM(K64))>0,LEN(TRIM(L64))>0,M64="Sim"),"Concluída",IF(H64=10,"Revisão ou dependências pendentes",IF(H64>0,"Em andamento","Pendente")))
A65: E064 | B65: Governança e aprovações | C65: Implementar decisão financeira compreensível | D65: UX, Backend e Aprovadores | E65: E018, E058, E060, E062, E063 | F65: Tela e transação de autorização de despesa | G65: Aprovador decide a versão apresentada dentro da alçada; resultado e impacto na verba são inequívocos. | H65: =COUNTIFS(Subetapas!A$2:A$1001,A65,Subetapas!G$2:G$1001,1) | I65: =IF(AND(N19="Concluída",N59="Concluída",N61="Concluída",N63="Concluída",N64="Concluída"),"Sim","Não") | M65: Não | N65: =IF(AND(H65=10,I65="Sim",LEN(TRIM(J65))>0,LEN(TRIM(K65))>0,LEN(TRIM(L65))>0,M65="Sim"),"Concluída",IF(H65=10,"Revisão ou dependências pendentes",IF(H65>0,"Em andamento","Pendente")))
A66: E065 | B66: Governança e aprovações | C66: Implementar aprovação formal da arte | D66: Marketing, Produção e UX | E66: E012, E018, E053, E054, E059, E063 | F66: Aceite de arte vinculado à produção | G66: Aprovação referencia arquivo e especificação exatos; não equivale automaticamente a autorização de despesa. | H66: =COUNTIFS(Subetapas!A$2:A$1001,A66,Subetapas!G$2:G$1001,1) | I66: =IF(AND(N13="Concluída",N19="Concluída",N54="Concluída",N55="Concluída",N60="Concluída",N64="Concluída"),"Sim","Não") | M66: Não | N66: =IF(AND(H66=10,I66="Sim",LEN(TRIM(J66))>0,LEN(TRIM(K66))>0,LEN(TRIM(L66))>0,M66="Sim"),"Concluída",IF(H66=10,"Revisão ou dependências pendentes",IF(H66>0,"Em andamento","Pendente")))
A67: E066 | B67: Governança e aprovações | C67: Tratar exceções sem perder governança | D67: Produto, Compras e UX | E67: E008, E018, E060, E064, E065 | F67: Fluxo explícito de exceções autorizadas | G67: Exceção possui motivo, autoridade, validade e efeito; não contorna isolamento ou proteção de dados. | H67: =COUNTIFS(Subetapas!A$2:A$1001,A67,Subetapas!G$2:G$1001,1) | I67: =IF(AND(N9="Concluída",N19="Concluída",N61="Concluída",N65="Concluída",N66="Concluída"),"Sim","Não") | M67: Não | N67: =IF(AND(H67=10,I67="Sim",LEN(TRIM(J67))>0,LEN(TRIM(K67))>0,LEN(TRIM(L67))>0,M67="Sim"),"Concluída",IF(H67=10,"Revisão ou dependências pendentes",IF(H67>0,"Em andamento","Pendente")))
A68: E067 | B68: Governança e aprovações | C68: Administrar substituições e delegações temporárias | D68: Segurança, Compras e UX | E68: E008, E012, E016, E063, E066 | F68: Delegação com escopo e prazo definidos | G68: Substituto só atua nas competências delegadas e dentro da vigência; histórico identifica delegação e ator real. | H68: =COUNTIFS(Subetapas!A$2:A$1001,A68,Subetapas!G$2:G$1001,1) | I68: =IF(AND(N9="Concluída",N13="Concluída",N17="Concluída",N64="Concluída",N67="Concluída"),"Sim","Não") | M68: Não | N68: =IF(AND(H68=10,I68="Sim",LEN(TRIM(J68))>0,LEN(TRIM(K68))>0,LEN(TRIM(L68))>0,M68="Sim"),"Concluída",IF(H68=10,"Revisão ou dependências pendentes",IF(H68>0,"Em andamento","Pendente")))
A69: E068 | B69: Governança e aprovações | C69: Tornar o histórico de decisões auditável | D69: Backend, UX e Auditoria | E69: E017, E018, E059, E064, E065, E066, E067 | F69: Histórico pesquisável de decisões e versões | G69: É possível reconstruir o que foi decidido, por quem, em qual contexto e com quais documentos. | H69: =COUNTIFS(Subetapas!A$2:A$1001,A69,Subetapas!G$2:G$1001,1) | I69: =IF(AND(N18="Concluída",N19="Concluída",N60="Concluída",N65="Concluída",N66="Concluída",N67="Concluída",N68="Concluída"),"Sim","Não") | M69: Não | N69: =IF(AND(H69=10,I69="Sim",LEN(TRIM(J69))>0,LEN(TRIM(K69))>0,LEN(TRIM(L69))>0,M69="Sim"),"Concluída",IF(H69=10,"Revisão ou dependências pendentes",IF(H69>0,"Em andamento","Pendente")))
A70: E069 | B70: Governança e aprovações | C70: Controlar revisões e cancelamentos | D70: UX, Backend e Operação | E70: E017, E059, E064, E065, E068 | F70: Mudança de pedido com impacto explícito | G70: Revisão ou cancelamento respeita estágio operacional, recalcula compromissos e preserva aprovações anteriores. | H70: =COUNTIFS(Subetapas!A$2:A$1001,A70,Subetapas!G$2:G$1001,1) | I70: =IF(AND(N18="Concluída",N60="Concluída",N65="Concluída",N66="Concluída",N69="Concluída"),"Sim","Não") | M70: Não | N70: =IF(AND(H70=10,I70="Sim",LEN(TRIM(J70))>0,LEN(TRIM(K70))>0,LEN(TRIM(L70))>0,M70="Sim"),"Concluída",IF(H70=10,"Revisão ou dependências pendentes",IF(H70>0,"Em andamento","Pendente")))
A71: E070 | B71: Governança e aprovações | C71: Implementar acompanhamento do ciclo do pedido | D71: UX, Backend e Frontend | E71: E007, E029, E061, E064, E065, E068, E069 | F71: Ciclo operacional com estado e próxima ação | G71: Frontend e backend usam estados compatíveis; uma etapa só avança mediante evento operacional válido. | H71: =COUNTIFS(Subetapas!A$2:A$1001,A71,Subetapas!G$2:G$1001,1) | I71: =IF(AND(N8="Concluída",N30="Concluída",N62="Concluída",N65="Concluída",N66="Concluída",N69="Concluída",N70="Concluída"),"Sim","Não") | M71: Não | N71: =IF(AND(H71=10,I71="Sim",LEN(TRIM(J71))>0,LEN(TRIM(K71))>0,LEN(TRIM(L71))>0,M71="Sim"),"Concluída",IF(H71=10,"Revisão ou dependências pendentes",IF(H71>0,"Em andamento","Pendente")))
A72: E071 | B72: Execução e pós-compra | C72: Formalizar a passagem do pedido ao fornecedor | D72: Operação, Comercial e Backend | E72: E007, E059, E064, E065, E070 | F72: Ordem de produção ou fornecimento inequívoca | G72: Fornecedor recebe a proposta, arte e distribuição aprovadas; aceite operacional é registrado. | H72: =COUNTIFS(Subetapas!A$2:A$1001,A72,Subetapas!G$2:G$1001,1) | I72: =IF(AND(N8="Concluída",N60="Concluída",N65="Concluída",N66="Concluída",N71="Concluída"),"Sim","Não") | M72: Não | N72: =IF(AND(H72=10,I72="Sim",LEN(TRIM(J72))>0,LEN(TRIM(K72))>0,LEN(TRIM(L72))>0,M72="Sim"),"Concluída",IF(H72=10,"Revisão ou dependências pendentes",IF(H72>0,"Em andamento","Pendente")))
A73: E072 | B73: Execução e pós-compra | C73: Acompanhar produção e controle de qualidade | D73: Operação, Produção e UX | E73: E054, E065, E070, E071 | F73: Marcos de produção baseados em confirmação | G73: Status e previsão refletem eventos reais; desvio relevante gera comunicação e tratamento definidos. | H73: =COUNTIFS(Subetapas!A$2:A$1001,A73,Subetapas!G$2:G$1001,1) | I73: =IF(AND(N55="Concluída",N66="Concluída",N71="Concluída",N72="Concluída"),"Sim","Não") | M73: Não | N73: =IF(AND(H73=10,I73="Sim",LEN(TRIM(J73))>0,LEN(TRIM(K73))>0,LEN(TRIM(L73))>0,M73="Sim"),"Concluída",IF(H73=10,"Revisão ou dependências pendentes",IF(H73>0,"Em andamento","Pendente")))
A74: E073 | B74: Execução e pós-compra | C74: Reconfirmar disponibilidade sem escrever no catálogo | D74: Comercial, Operação e Backend | E74: E003, E048, E059, E069, E071 | F74: Processo de reconfirmação de oferta | G74: Consulta não é apresentada como reserva; indisponibilidade resulta em revisão autorizada ou alternativa. | H74: =COUNTIFS(Subetapas!A$2:A$1001,A74,Subetapas!G$2:G$1001,1) | I74: =IF(AND(N4="Concluída",N49="Concluída",N60="Concluída",N70="Concluída",N72="Concluída"),"Sim","Não") | M74: Não | N74: =IF(AND(H74=10,I74="Sim",LEN(TRIM(J74))>0,LEN(TRIM(K74))>0,LEN(TRIM(L74))>0,M74="Sim"),"Concluída",IF(H74=10,"Revisão ou dependências pendentes",IF(H74>0,"Em andamento","Pendente")))
A75: E074 | B75: Execução e pós-compra | C75: Preparar expedição e entregas por destino | D75: Logística, UX e Backend | E75: E056, E070, E071, E072, E073 | F75: Plano de expedição por volume e destino | G75: Quantidades expedidas e documentos correspondem ao pedido; expedição parcial mantém saldo rastreável. | H75: =COUNTIFS(Subetapas!A$2:A$1001,A75,Subetapas!G$2:G$1001,1) | I75: =IF(AND(N57="Concluída",N71="Concluída",N72="Concluída",N73="Concluída",N74="Concluída"),"Sim","Não") | M75: Não | N75: =IF(AND(H75=10,I75="Sim",LEN(TRIM(J75))>0,LEN(TRIM(K75))>0,LEN(TRIM(L75))>0,M75="Sim"),"Concluída",IF(H75=10,"Revisão ou dependências pendentes",IF(H75>0,"Em andamento","Pendente")))
A76: E075 | B76: Execução e pós-compra | C76: Oferecer rastreio e previsão confiáveis | D76: UX, Logística e Frontend | E76: E029, E038, E070, E074 | F76: Acompanhamento por entrega e ocorrência | G76: Dados de rastreio têm origem e atualização identificadas; entrega atrasada não aparece como concluída. | H76: =COUNTIFS(Subetapas!A$2:A$1001,A76,Subetapas!G$2:G$1001,1) | I76: =IF(AND(N30="Concluída",N39="Concluída",N71="Concluída",N75="Concluída"),"Sim","Não") | M76: Não | N76: =IF(AND(H76=10,I76="Sim",LEN(TRIM(J76))>0,LEN(TRIM(K76))>0,LEN(TRIM(L76))>0,M76="Sim"),"Concluída",IF(H76=10,"Revisão ou dependências pendentes",IF(H76>0,"Em andamento","Pendente")))
A77: E076 | B77: Execução e pós-compra | C77: Registrar recebimento e conferência | D77: Operação do PA, UX e Backend | E77: E012, E068, E074, E075 | F77: Recebimento por quantidade e destino | G77: Conferência registra o que realmente chegou; confirmação indevida não encerra saldo pendente. | H77: =COUNTIFS(Subetapas!A$2:A$1001,A77,Subetapas!G$2:G$1001,1) | I77: =IF(AND(N13="Concluída",N69="Concluída",N75="Concluída",N76="Concluída"),"Sim","Não") | M77: Não | N77: =IF(AND(H77=10,I77="Sim",LEN(TRIM(J77))>0,LEN(TRIM(K77))>0,LEN(TRIM(L77))>0,M77="Sim"),"Concluída",IF(H77=10,"Revisão ou dependências pendentes",IF(H77>0,"Em andamento","Pendente")))
A78: E077 | B78: Execução e pós-compra | C78: Resolver faltas, avarias e devoluções | D78: Atendimento, Logística e UX | E78: E007, E029, E069, E075, E076 | F78: Gestão de ocorrências com responsável e solução | G78: Comprador acompanha a resolução; ocorrência só encerra quando a solução acordada está registrada. | H78: =COUNTIFS(Subetapas!A$2:A$1001,A78,Subetapas!G$2:G$1001,1) | I78: =IF(AND(N8="Concluída",N30="Concluída",N70="Concluída",N76="Concluída",N77="Concluída"),"Sim","Não") | M78: Não | N78: =IF(AND(H78=10,I78="Sim",LEN(TRIM(J78))>0,LEN(TRIM(K78))>0,LEN(TRIM(L78))>0,M78="Sim"),"Concluída",IF(H78=10,"Revisão ou dependências pendentes",IF(H78>0,"Em andamento","Pendente")))
A79: E078 | B79: Execução e pós-compra | C79: Conciliar documentos financeiros e entrega | D79: Financeiro, Compras e Backend | E79: E017, E058, E068, E069, E076, E077 | F79: Conciliação entre contratação, recebimento e cobrança | G79: Valores e documentos têm vínculo verificável; divergência impede encerramento financeiro indevido. | H79: =COUNTIFS(Subetapas!A$2:A$1001,A79,Subetapas!G$2:G$1001,1) | I79: =IF(AND(N18="Concluída",N59="Concluída",N69="Concluída",N70="Concluída",N77="Concluída",N78="Concluída"),"Sim","Não") | M79: Não | N79: =IF(AND(H79=10,I79="Sim",LEN(TRIM(J79))>0,LEN(TRIM(K79))>0,LEN(TRIM(L79))>0,M79="Sim"),"Concluída",IF(H79=10,"Revisão ou dependências pendentes",IF(H79>0,"Em andamento","Pendente")))
A80: E079 | B80: Execução e pós-compra | C80: Facilitar recompra com revalidação | D80: UX, Comercial e Frontend | E80: E003, E050, E059, E073, E076, E078 | F80: Recompra que cria nova proposta | G80: Histórico acelera a seleção, mas preço, disponibilidade, arte e prazo são verificados novamente. | H80: =COUNTIFS(Subetapas!A$2:A$1001,A80,Subetapas!G$2:G$1001,1) | I80: =IF(AND(N4="Concluída",N51="Concluída",N60="Concluída",N74="Concluída",N77="Concluída",N79="Concluída"),"Sim","Não") | M80: Não | N80: =IF(AND(H80=10,I80="Sim",LEN(TRIM(J80))>0,LEN(TRIM(K80))>0,LEN(TRIM(L80))>0,M80="Sim"),"Concluída",IF(H80=10,"Revisão ou dependências pendentes",IF(H80>0,"Em andamento","Pendente")))
A81: E080 | B81: Execução e pós-compra | C81: Oferecer ajuda contextual e atendimento | D81: Conteúdo UX, Atendimento e Frontend | E81: E026, E028, E029, E061, E070, E077, E079 | F81: Ajuda integrada à tarefa | G81: Usuário encontra orientação e atendimento no contexto correto, com retorno rastreável. | H81: =COUNTIFS(Subetapas!A$2:A$1001,A81,Subetapas!G$2:G$1001,1) | I81: =IF(AND(N27="Concluída",N29="Concluída",N30="Concluída",N62="Concluída",N71="Concluída",N78="Concluída",N80="Concluída"),"Sim","Não") | M81: Não | N81: =IF(AND(H81=10,I81="Sim",LEN(TRIM(J81))>0,LEN(TRIM(K81))>0,LEN(TRIM(L81))>0,M81="Sim"),"Concluída",IF(H81=10,"Revisão ou dependências pendentes",IF(H81>0,"Em andamento","Pendente")))
A82: E081 | B82: Qualidade e validação | C82: Auditar acessibilidade da jornada completa | D82: Especialista em acessibilidade e QA | E82: E040, E041, E046, E061, E064, E065, E076, E080 | F82: Relatório WCAG com evidências e correções | G82: Critérios aplicáveis são verificados por automação e avaliação manual; falhas impeditivas estão resolvidas. | H82: =COUNTIFS(Subetapas!A$2:A$1001,A82,Subetapas!G$2:G$1001,1) | I82: =IF(AND(N41="Concluída",N42="Concluída",N47="Concluída",N62="Concluída",N65="Concluída",N66="Concluída",N77="Concluída",N81="Concluída"),"Sim","Não") | M82: Não | N82: =IF(AND(H82=10,I82="Sim",LEN(TRIM(J82))>0,LEN(TRIM(K82))>0,LEN(TRIM(L82))>0,M82="Sim"),"Concluída",IF(H82=10,"Revisão ou dependências pendentes",IF(H82>0,"Em andamento","Pendente")))
A83: E082 | B83: Qualidade e validação | C83: Validar uso móvel em situações reais | D83: Pesquisa UX, Frontend e QA | E83: E041, E045, E046, E061, E063, E065, E075, E076, E081 | F83: Jornadas móveis verificadas | G83: Solicitar, aprovar e receber são possíveis sem gestos exclusivos ou conteúdo essencial oculto. | H83: =COUNTIFS(Subetapas!A$2:A$1001,A83,Subetapas!G$2:G$1001,1) | I83: =IF(AND(N42="Concluída",N46="Concluída",N47="Concluída",N62="Concluída",N64="Concluída",N66="Concluída",N76="Concluída",N77="Concluída",N82="Concluída"),"Sim","Não") | M83: Não | N83: =IF(AND(H83=10,I83="Sim",LEN(TRIM(J83))>0,LEN(TRIM(K83))>0,LEN(TRIM(L83))>0,M83="Sim"),"Concluída",IF(H83=10,"Revisão ou dependências pendentes",IF(H83>0,"Em andamento","Pendente")))
A84: E083 | B84: Qualidade e validação | C84: Testar responsividade e conteúdo extremo | D84: Design, Frontend e QA | E84: E032, E033, E038, E081, E082 | F84: Matriz visual com dados extremos | G84: Conteúdo continua compreensível sem cortes indevidos, sobreposição ou perda de ações importantes. | H84: =COUNTIFS(Subetapas!A$2:A$1001,A84,Subetapas!G$2:G$1001,1) | I84: =IF(AND(N33="Concluída",N34="Concluída",N39="Concluída",N82="Concluída",N83="Concluída"),"Sim","Não") | M84: Não | N84: =IF(AND(H84=10,I84="Sim",LEN(TRIM(J84))>0,LEN(TRIM(K84))>0,LEN(TRIM(L84))>0,M84="Sim"),"Concluída",IF(H84=10,"Revisão ou dependências pendentes",IF(H84>0,"Em andamento","Pendente")))
A85: E084 | B85: Qualidade e validação | C85: Otimizar desempenho percebido e carregamento | D85: Frontend, Infraestrutura e UX | E85: E019, E020, E039, E043, E046, E061, E083 | F85: Orçamento de desempenho e medições reproduzíveis | G85: Jornadas atendem o orçamento definido em homologação; métricas de campo permanecem separadas das medições de laboratório. | H85: =COUNTIFS(Subetapas!A$2:A$1001,A85,Subetapas!G$2:G$1001,1) | I85: =IF(AND(N20="Concluída",N21="Concluída",N40="Concluída",N44="Concluída",N47="Concluída",N62="Concluída",N84="Concluída"),"Sim","Não") | M85: Não | N85: =IF(AND(H85=10,I85="Sim",LEN(TRIM(J85))>0,LEN(TRIM(K85))>0,LEN(TRIM(L85))>0,M85="Sim"),"Concluída",IF(H85=10,"Revisão ou dependências pendentes",IF(H85>0,"Em andamento","Pendente")))
A86: E085 | B86: Qualidade e validação | C86: Validar resiliência e preservação do trabalho | D86: Backend, Frontend e QA | E86: E020, E028, E057, E061, E064, E070, E084 | F86: Fluxos recuperáveis sob falha | G86: Indisponibilidade e reenvio não perdem rascunhos nem duplicam compromissos de compra. | H86: =COUNTIFS(Subetapas!A$2:A$1001,A86,Subetapas!G$2:G$1001,1) | I86: =IF(AND(N21="Concluída",N29="Concluída",N58="Concluída",N62="Concluída",N65="Concluída",N71="Concluída",N85="Concluída"),"Sim","Não") | M86: Não | N86: =IF(AND(H86=10,I86="Sim",LEN(TRIM(J86))>0,LEN(TRIM(K86))>0,LEN(TRIM(L86))>0,M86="Sim"),"Concluída",IF(H86=10,"Revisão ou dependências pendentes",IF(H86>0,"Em andamento","Pendente")))
A87: E086 | B87: Qualidade e validação | C87: Verificar segurança das jornadas integradas | D87: Segurança, Backend e QA | E87: E013, E018, E053, E064, E065, E067, E068, E085 | F87: Validação de autorização ponta a ponta | G87: Tentativas de acesso cruzado, alteração de ator ou manipulação de versão são negadas no servidor. | H87: =COUNTIFS(Subetapas!A$2:A$1001,A87,Subetapas!G$2:G$1001,1) | I87: =IF(AND(N14="Concluída",N19="Concluída",N54="Concluída",N65="Concluída",N66="Concluída",N68="Concluída",N69="Concluída",N86="Concluída"),"Sim","Não") | M87: Não | N87: =IF(AND(H87=10,I87="Sim",LEN(TRIM(J87))>0,LEN(TRIM(K87))>0,LEN(TRIM(L87))>0,M87="Sim"),"Concluída",IF(H87=10,"Revisão ou dependências pendentes",IF(H87>0,"Em andamento","Pendente")))
A88: E087 | B88: Qualidade e validação | C88: Validar privacidade e ciclo de vida dos dados | D88: Responsável por privacidade, Produto e Segurança | E88: E008, E011, E020, E053, E068, E078, E080, E086 | F88: Mapa de dados e práticas aprovadas | G88: Coleta, acesso, retenção e atendimento de solicitações possuem finalidade e responsabilidade definidas. | H88: =COUNTIFS(Subetapas!A$2:A$1001,A88,Subetapas!G$2:G$1001,1) | I88: =IF(AND(N9="Concluída",N12="Concluída",N21="Concluída",N54="Concluída",N69="Concluída",N79="Concluída",N81="Concluída",N87="Concluída"),"Sim","Não") | M88: Não | N88: =IF(AND(H88=10,I88="Sim",LEN(TRIM(J88))>0,LEN(TRIM(K88))>0,LEN(TRIM(L88))>0,M88="Sim"),"Concluída",IF(H88=10,"Revisão ou dependências pendentes",IF(H88>0,"Em andamento","Pendente")))
A89: E088 | B89: Qualidade e validação | C89: Conduzir testes de usabilidade com tarefas completas | D89: Pesquisa UX, Compras e Marketing | E89: E005, E030, E061, E064, E065, E076, E079, E081, E082, E085 | F89: Resultados observados e correções priorizadas | G89: Problemas que impedem concluir tarefas críticas estão resolvidos e reavaliados com participantes adequados. | H89: =COUNTIFS(Subetapas!A$2:A$1001,A89,Subetapas!G$2:G$1001,1) | I89: =IF(AND(N6="Concluída",N31="Concluída",N62="Concluída",N65="Concluída",N66="Concluída",N77="Concluída",N80="Concluída",N82="Concluída",N83="Concluída",N86="Concluída"),"Sim","Não") | M89: Não | N89: =IF(AND(H89=10,I89="Sim",LEN(TRIM(J89))>0,LEN(TRIM(K89))>0,LEN(TRIM(L89))>0,M89="Sim"),"Concluída",IF(H89=10,"Revisão ou dependências pendentes",IF(H89>0,"Em andamento","Pendente")))
A90: E089 | B90: Qualidade e validação | C90: Construir indicadores operacionais verdadeiros | D90: Dados, Produto e UX | E90: E009, E020, E062, E068, E076, E077, E078, E088 | F90: Painel de operação com origem demonstrável | G90: Indicadores reconciliam com eventos e amostra de pedidos; dados insuficientes aparecem como não medidos. | H90: =COUNTIFS(Subetapas!A$2:A$1001,A90,Subetapas!G$2:G$1001,1) | I90: =IF(AND(N10="Concluída",N21="Concluída",N63="Concluída",N69="Concluída",N77="Concluída",N78="Concluída",N79="Concluída",N89="Concluída"),"Sim","Não") | M90: Não | N90: =IF(AND(H90=10,I90="Sim",LEN(TRIM(J90))>0,LEN(TRIM(K90))>0,LEN(TRIM(L90))>0,M90="Sim"),"Concluída",IF(H90=10,"Revisão ou dependências pendentes",IF(H90>0,"Em andamento","Pendente")))
A91: E090 | B91: Qualidade e validação | C91: Concluir homologação funcional e de conteúdo | D91: QA, Conteúdo, UX e Engenharia | E91: E019, E041, E060, E070, E078, E081, E083, E084, E085, E086, E087, E088, E089 | F91: Relatório integrado de homologação | G91: Cenários críticos passam; conteúdo, formatos e estados refletem regras e dados do ambiente testado. | H91: =COUNTIFS(Subetapas!A$2:A$1001,A91,Subetapas!G$2:G$1001,1) | I91: =IF(AND(N20="Concluída",N42="Concluída",N61="Concluída",N71="Concluída",N79="Concluída",N82="Concluída",N84="Concluída",N85="Concluída",N86="Concluída",N87="Concluída",N88="Concluída",N89="Concluída",N90="Concluída"),"Sim","Não") | M91: Não | N91: =IF(AND(H91=10,I91="Sim",LEN(TRIM(J91))>0,LEN(TRIM(K91))>0,LEN(TRIM(L91))>0,M91="Sim"),"Concluída",IF(H91=10,"Revisão ou dependências pendentes",IF(H91>0,"Em andamento","Pendente")))
A92: E091 | B92: Produção e expansão | C92: Ensaiar a compra integral antes do piloto | D92: Produto, Compras, Marketing e Operação | E92: E007, E017, E018, E056, E060, E064, E065, E071, E073, E076, E078, E090 | F92: Ensaio completo com exceções | G92: Uma compra atravessa todas as áreas e concilia valores e quantidades, sem intervenção técnica oculta. | H92: =COUNTIFS(Subetapas!A$2:A$1001,A92,Subetapas!G$2:G$1001,1) | I92: =IF(AND(N8="Concluída",N18="Concluída",N19="Concluída",N57="Concluída",N61="Concluída",N65="Concluída",N66="Concluída",N72="Concluída",N74="Concluída",N77="Concluída",N79="Concluída",N91="Concluída"),"Sim","Não") | M92: Não | N92: =IF(AND(H92=10,I92="Sim",LEN(TRIM(J92))>0,LEN(TRIM(K92))>0,LEN(TRIM(L92))>0,M92="Sim"),"Concluída",IF(H92=10,"Revisão ou dependências pendentes",IF(H92>0,"Em andamento","Pendente")))
A93: E092 | B93: Produção e expansão | C93: Revisar a experiência final e a aplicação da marca | D93: Direção de design, Marca e Produto | E93: E031, E040, E081, E082, E083, E088, E090, E091 | F93: Aceite de experiência e identidade da release | G93: Telas, documentos e comunicações seguem a direção aprovada e suportam as tarefas prioritárias. | H93: =COUNTIFS(Subetapas!A$2:A$1001,A93,Subetapas!G$2:G$1001,1) | I93: =IF(AND(N32="Concluída",N41="Concluída",N82="Concluída",N83="Concluída",N84="Concluída",N89="Concluída",N91="Concluída",N92="Concluída"),"Sim","Não") | M93: Não | N93: =IF(AND(H93=10,I93="Sim",LEN(TRIM(J93))>0,LEN(TRIM(K93))>0,LEN(TRIM(L93))>0,M93="Sim"),"Concluída",IF(H93=10,"Revisão ou dependências pendentes",IF(H93>0,"Em andamento","Pendente")))
A94: E093 | B94: Produção e expansão | C94: Preparar a cooperativa piloto e seus dados | D94: Produto, Administração e Dados | E94: E008, E011, E012, E016, E017, E087, E091, E092 | F94: Cadastro reconciliado da cooperativa piloto | G94: Unidades, papéis, políticas, endereços e verbas estão conferidos antes de receber compras reais. | H94: =COUNTIFS(Subetapas!A$2:A$1001,A94,Subetapas!G$2:G$1001,1) | I94: =IF(AND(N9="Concluída",N12="Concluída",N13="Concluída",N17="Concluída",N18="Concluída",N88="Concluída",N92="Concluída",N93="Concluída"),"Sim","Não") | M94: Não | N94: =IF(AND(H94=10,I94="Sim",LEN(TRIM(J94))>0,LEN(TRIM(K94))>0,LEN(TRIM(L94))>0,M94="Sim"),"Concluída",IF(H94=10,"Revisão ou dependências pendentes",IF(H94>0,"Em andamento","Pendente")))
A95: E094 | B95: Produção e expansão | C95: Preparar operação, suporte e treinamento | D95: Operação, Atendimento e UX | E95: E007, E029, E070, E077, E078, E080, E091, E093 | F95: Equipe preparada para executar e apoiar o piloto | G95: Responsáveis conseguem concluir suas tarefas e encaminhar falhas pelos procedimentos documentados. | H95: =COUNTIFS(Subetapas!A$2:A$1001,A95,Subetapas!G$2:G$1001,1) | I95: =IF(AND(N8="Concluída",N30="Concluída",N71="Concluída",N78="Concluída",N79="Concluída",N81="Concluída",N92="Concluída",N94="Concluída"),"Sim","Não") | M95: Não | N95: =IF(AND(H95=10,I95="Sim",LEN(TRIM(J95))>0,LEN(TRIM(K95))>0,LEN(TRIM(L95))>0,M95="Sim"),"Concluída",IF(H95=10,"Revisão ou dependências pendentes",IF(H95>0,"Em andamento","Pendente")))
A96: E095 | B96: Produção e expansão | C96: Preparar release e decisão de lançamento | D96: Liderança técnica, Produto e Operação | E96: E019, E020, E086, E087, E090, E091, E092, E093, E094 | F96: Release candidata e decisão registrada | G96: Não existem bloqueadores críticos pendentes; deploy, rollback, suporte e autorização operacional estão preparados. | H96: =COUNTIFS(Subetapas!A$2:A$1001,A96,Subetapas!G$2:G$1001,1) | I96: =IF(AND(N20="Concluída",N21="Concluída",N87="Concluída",N88="Concluída",N91="Concluída",N92="Concluída",N93="Concluída",N94="Concluída",N95="Concluída"),"Sim","Não") | M96: Não | N96: =IF(AND(H96=10,I96="Sim",LEN(TRIM(J96))>0,LEN(TRIM(K96))>0,LEN(TRIM(L96))>0,M96="Sim"),"Concluída",IF(H96=10,"Revisão ou dependências pendentes",IF(H96>0,"Em andamento","Pendente")))
A97: E096 | B97: Produção e expansão | C97: Publicar o piloto e verificar produção | D97: Infraestrutura, Produto e Operação | E97: E095 | F97: Portal piloto publicado e verificável | G97: Domínio e commit produtivos estão confirmados; fluxos essenciais funcionam com responsáveis reais e monitoramento ativo. | H97: =COUNTIFS(Subetapas!A$2:A$1001,A97,Subetapas!G$2:G$1001,1) | I97: =IF(AND(N96="Concluída"),"Sim","Não") | M97: Não | N97: =IF(AND(H97=10,I97="Sim",LEN(TRIM(J97))>0,LEN(TRIM(K97))>0,LEN(TRIM(L97))>0,M97="Sim"),"Concluída",IF(H97=10,"Revisão ou dependências pendentes",IF(H97>0,"Em andamento","Pendente")))
A98: E097 | B98: Produção e expansão | C98: Acompanhar a primeira compra real até o recebimento | D98: Produto, Cooperativa piloto e Operação | E98: E064, E065, E073, E076, E078, E094, E096 | F98: Primeira compra real conciliada | G98: Pedido real autorizado é produzido, entregue e conciliado, com histórico e saldo verificáveis. | H98: =COUNTIFS(Subetapas!A$2:A$1001,A98,Subetapas!G$2:G$1001,1) | I98: =IF(AND(N65="Concluída",N66="Concluída",N74="Concluída",N77="Concluída",N79="Concluída",N95="Concluída",N97="Concluída"),"Sim","Não") | M98: Não | N98: =IF(AND(H98=10,I98="Sim",LEN(TRIM(J98))>0,LEN(TRIM(K98))>0,LEN(TRIM(L98))>0,M98="Sim"),"Concluída",IF(H98=10,"Revisão ou dependências pendentes",IF(H98>0,"Em andamento","Pendente")))
A99: E098 | B99: Produção e expansão | C99: Medir o piloto e corrigir fricções comprovadas | D99: Produto, Dados, UX e Operação | E99: E009, E084, E088, E089, E097 | F99: Avaliação do piloto com correções verificadas | G99: Resultados têm amostra e período definidos; ajustes prioritários demonstram melhoria ou limitação explicitamente registrada. | H99: =COUNTIFS(Subetapas!A$2:A$1001,A99,Subetapas!G$2:G$1001,1) | I99: =IF(AND(N10="Concluída",N85="Concluída",N89="Concluída",N90="Concluída",N98="Concluída"),"Sim","Não") | M99: Não | N99: =IF(AND(H99=10,I99="Sim",LEN(TRIM(J99))>0,LEN(TRIM(K99))>0,LEN(TRIM(L99))>0,M99="Sim"),"Concluída",IF(H99=10,"Revisão ou dependências pendentes",IF(H99>0,"Em andamento","Pendente")))
A100: E099 | B100: Produção e expansão | C100: Validar uma segunda cooperativa com regras diferentes | D100: Produto, Compras e Engenharia | E100: E008, E012, E013, E017, E067, E093, E098 | F100: Configuração e operação de segunda cooperativa | G100: Variação de política funciona sem duplicar aplicação; isolamento e diferenças de regra são demonstrados. | H100: =COUNTIFS(Subetapas!A$2:A$1001,A100,Subetapas!G$2:G$1001,1) | I100: =IF(AND(N9="Concluída",N13="Concluída",N14="Concluída",N18="Concluída",N68="Concluída",N94="Concluída",N99="Concluída"),"Sim","Não") | M100: Não | N100: =IF(AND(H100=10,I100="Sim",LEN(TRIM(J100))>0,LEN(TRIM(K100))>0,LEN(TRIM(L100))>0,M100="Sim"),"Concluída",IF(H100=10,"Revisão ou dependências pendentes",IF(H100>0,"Em andamento","Pendente")))
...

Sheet Subetapas
A1: Etapa | B1: ID da subetapa | C1: Ação obrigatória | D1: Responsável funcional | E1: Estado informado | F1: Evidência | G1: Verificada | H1: Data do registro
A2: E001 | B2: E001.01 | C2: Registrar o commit de referência e os links do diagnóstico anterior. | D2: Liderança técnica e Produto | E2: Pendente | G2: =IF(AND(E2="Concluída",LEN(TRIM(F2))>0),1,0)
A3: E001 | B3: E001.02 | C3: Identificar domínio produtivo, prévia e ambiente segregado de testes. | D3: Liderança técnica e Produto | E3: Pendente | G3: =IF(AND(E3="Concluída",LEN(TRIM(F3))>0),1,0)
A4: E001 | B4: E001.03 | C4: Confirmar os identificadores dos dois bancos com metadados seguros. | D4: Liderança técnica e Produto | E4: Pendente | G4: =IF(AND(E4="Concluída",LEN(TRIM(F4))>0),1,0)
A5: E001 | B5: E001.04 | C5: Relacionar funções publicadas com as funções presentes no repositório. | D5: Liderança técnica e Produto | E5: Pendente | G5: =IF(AND(E5="Concluída",LEN(TRIM(F5))>0),1,0)
A6: E001 | B6: E001.05 | C6: Classificar telas entre demonstradas, parcialmente funcionais e sem evidência. | D6: Liderança técnica e Produto | E6: Pendente | G6: =IF(AND(E6="Concluída",LEN(TRIM(F6))>0),1,0)
A7: E001 | B7: E001.06 | C7: Registrar os resultados reais de build, tipos e testes disponíveis. | D7: Liderança técnica e Produto | E7: Pendente | G7: =IF(AND(E7="Concluída",LEN(TRIM(F7))>0),1,0)
A8: E001 | B8: E001.07 | C8: Catalogar divergências entre documentação, configuração e comportamento observado. | D8: Liderança técnica e Produto | E8: Pendente | G8: =IF(AND(E8="Concluída",LEN(TRIM(F8))>0),1,0)
A9: E001 | B9: E001.08 | C9: Mapear responsáveis por produto, marca, compra, operação e infraestrutura. | D9: Liderança técnica e Produto | E9: Pendente | G9: =IF(AND(E9="Concluída",LEN(TRIM(F9))>0),1,0)
A10: E001 | B10: E001.09 | C10: Criar um registro de decisões com data, justificativa e impacto. | D10: Liderança técnica e Produto | E10: Pendente | G10: =IF(AND(E10="Concluída",LEN(TRIM(F10))>0),1,0)
A11: E001 | B11: E001.10 | C11: Revisar o inventário e anexar evidências de cada afirmação operacional. | D11: Liderança técnica e Produto | E11: Pendente | G11: =IF(AND(E11="Concluída",LEN(TRIM(F11))>0),1,0)
A12: E002 | B12: E002.01 | C12: Verificar por inventário seguro se migrate-helper está publicado. | D12: Engenharia de segurança | E12: Pendente | G12: =IF(AND(E12="Concluída",LEN(TRIM(F12))>0),1,0)
A13: E002 | B13: E002.02 | C13: Inspecionar a configuração de autorização sem invocar retorno de segredos. | D13: Engenharia de segurança | E13: Pendente | G13: =IF(AND(E13="Concluída",LEN(TRIM(F13))>0),1,0)
... A1001: E100 | B1001: E100.10 | C1001: Registrar o aceite final da implantação com responsáveis, data e evidências verificáveis. | D1001: Produto, Design, Engenharia e Operação | E1001: Pendente | G1001: =IF(AND(E1001="Concluída",LEN(TRIM(F1001))>0),1,0)

Sheet Referências
A1: ID | B1: Título | C1: Origem | D1: URL | E1: Aplicação e limite
A2: R01 | B2: Diagnóstico do portal Sicoob e anexos | C2: Pesquisa do projeto, 11/09/2026 | D2: https://github.com/adm01-debug/Brindes_Sicoob_V2/blob/ec5cfaf5c2de844458c0105d8ad40c35f1eb9c14/docs/pesquisa/2026-09-11/dossie.md | E2: Reaproveitamento, riscos, políticas locais e perfis funcionais; não certifica produção.
A3: R02 | B3: Guia da marca Sicoob | C3: Março/2023; versão vigente a confirmar | D3: https://portalcredicope.com.br/uploads/DOCUMENTOS/GUIA_DA_MARCA_-SICOOB_marco_23.pdf | E3: Direção visual; a etapa 31 exige validação atual dos ativos e da especificação.
A4: R03 | B4: Heurísticas de usabilidade de Jakob Nielsen | C4: NN/g; revisão de 30/01/2024 | D4: https://www.nngroup.com/articles/ten-usability-heuristics/ | E4: Revisão de clareza, consistência, controle, prevenção e recuperação de erros.
A5: R04 | B5: WCAG 2.2 | C5: W3C; referência normativa consultada em 11/09/2026 | D5: https://www.w3.org/TR/WCAG22/ | E5: Meta de conformidade AA; exige verificar todos os critérios aplicáveis, não apenas automação.
A6: R05 | B6: Contraste mínimo de texto | C6: W3C WAI; consultado em 11/09/2026 | D6: https://www.w3.org/WAI/WCAG22/Understanding/contrast-minimum | E6: 4,5:1 para texto normal e 3:1 para texto grande, com exceções normativas.
A7: R06 | B7: Contraste de informação não textual | C7: W3C WAI; consultado em 11/09/2026 | D7: https://www.w3.org/WAI/WCAG22/Understanding/non-text-contrast.html | E7: Verificação de informação visual essencial de controles e gráficos.
A8: R07 | B8: Tamanho mínimo de alvo de interação | C8: W3C WAI; consultado em 11/09/2026 | D8: https://www.w3.org/WAI/WCAG22/Understanding/target-size-minimum | E8: Mínimo de 24 × 24 CSS px ou condições de exceção; 44 px é preferência proposta para ações principais.
A9: R08 | B9: Foco não encoberto | C9: W3C WAI; consultado em 11/09/2026 | D9: https://www.w3.org/WAI/WCAG22/Understanding/focus-not-obscured-minimum.html | E9: Evitar que conteúdo fixo esconda o componente com foco, observadas as condições do critério.
A10: R09 | B10: Web Vitals | C10: Google web.dev; consultado em 11/09/2026 | D10: https://web.dev/articles/vitals | E10: Referências de campo: LCP 2,5 s, INP 200 ms e CLS 0,1 no percentil 75; laboratório é outra evidência.
A11: R10 | B11: Concluir múltiplas tarefas | C11: GOV.UK Design System; consultado em 11/09/2026 | D11: https://design-system.service.gov.uk/patterns/complete-multiple-tasks/ | E11: Organização de tarefas e estados; aplicação adaptada às jornadas institucionais do portal.
